README.md
setup.py
kbucket/__init__.py
kbucket/kbucketclient.py
kbucket/steady_download_and_compute_sha1.py
kbucket.egg-info/PKG-INFO
kbucket.egg-info/SOURCES.txt
kbucket.egg-info/dependency_links.txt
kbucket.egg-info/requires.txt
kbucket.egg-info/top_level.txt