Metadata-Version: 1.1
Name: kbucket
Version: 0.12.5
Summary: Python client for kbucket
Home-page: https://github.com/flatironinstitute/kbucket
Author: Jeremy Magland
Author-email: jmagland@flatironinstitute.org
License: UNKNOWN
Platform: UNKNOWN
Classifier: Programming Language :: Python :: 3
Classifier: License :: OSI Approved :: Apache Software License
Classifier: Operating System :: OS Independent
